setup.py
demographics/__init__.py
demographics.egg-info/PKG-INFO
demographics.egg-info/SOURCES.txt
demographics.egg-info/dependency_links.txt
demographics.egg-info/top_level.txt
demographics.egg-info/zip-safe
demographics/data/__init__.py
demographics/data/us/__init__.py
demographics/data/us/gender.py
demographics/data/us/race.py