Metadata-Version: 1.0
Name: demographics
Version: 0.0.1
Summary: Estimate user's demographics from their name or email address.
Home-page: UNKNOWN
Author: Adam DePrince
Author-email: adeprince@nypublicradio.org
License: MIT
Platform: UNKNOWN
